README.txt
setup.cfg
setup.py
collective/__init__.py
collective.flattr.egg-info/PKG-INFO
collective.flattr.egg-info/SOURCES.txt
collective.flattr.egg-info/dependency_links.txt
collective.flattr.egg-info/entry_points.txt
collective.flattr.egg-info/namespace_packages.txt
collective.flattr.egg-info/not-zip-safe
collective.flattr.egg-info/paster_plugins.txt
collective.flattr.egg-info/requires.txt
collective.flattr.egg-info/top_level.txt
collective/flattr/__init__.py
collective/flattr/extender.py
collective/flattr/handlers.py
collective/flattr/interfaces.py
collective/flattr/vocab.py
collective/flattr/widget.py
collective/flattr/browser/__init__.py
collective/flattr/browser/controlpanel.py
collective/flattr/browser/flattr.py
collective/flattr/browser/flattrhelper.py
collective/flattr/browser/viewlets.py
collective/flattr/migrations/__init__.py
collective/flattr/migrations/migrations.py
collective/flattr/portlets/__init__.py
collective/flattr/portlets/flattrportlet.py
collective/flattr/tests/__init__.py
collective/flattr/tests/base.py
collective/flattr/tests/mocks.py
collective/flattr/tests/test_controlpanel.py
collective/flattr/tests/test_controlpanel_call.py
collective/flattr/tests/test_flattr_helper_view.py
collective/flattr/tests/test_flattr_view.py
collective/flattr/tests/test_flattr_viewlet.py
collective/flattr/tests/test_flattrportlet.py