Metadata-Version: 1.0
Name: collective.flattr
Version: 0.2
Summary: Integrate http://flattr.com/ into Plone
Home-page: https://launchpad.net/collective.flattr/
Author: Christoph Glaubitz
Author-email: chris@chrigl.de
License: GPL
Keywords: web zope plone flattr
Platform: UNKNOWN
Classifier: Framework :: Plone
Classifier: Programming Language :: Python
